{"attributes": {"fullName": "qx.ui.mobile.form.Form", "packageName": "qx.ui.mobile.form", "type": "class", "name": "Form", "superClass": "qx.ui.form.Form"}, "type": "class", "children": [{"attributes": {"text": "<p>Representation of a form. A form widget can contain one or more {@link Row} widgets.</p>\n\n<p><strong>Example</strong></p>\n\n<p>Here is a little example of how to use the widget.</p>\n\n<pre class=\"javascript\">\n  var title = new qx.ui.mobile.form.Title(\"Group\");\n  var form = new qx.ui.mobile.form.Form();\n  form.add(new qx.ui.mobile.form.TextField(), \"Username: \");\n\n  this.getRoot.add(title);\n  this.getRoot.add(new qx.ui.mobile.form.renderer.Single(form));\n</pre>\n\n<p>This example creates a form and adds a row with a text field in it.</p>"}, "type": "desc"}, {"attributes": {}, "type": "constructor", "children": [{"attributes": {"docFrom": "qx.core.Object", "line": 48, "isCtor": true, "overriddenFrom": "qx.ui.form.Form", "name": "ctor"}, "type": "method"}]}, {"attributes": {}, "type": "methods", "children": [{"attributes": {"access": "protected", "docFrom": "qx.ui.form.Form", "line": 64, "overriddenFrom": "qx.ui.form.Form", "name": "_createResetter"}, "type": "method"}, {"attributes": {"line": 75, "name": "setRenderer"}, "type": "method", "children": [{"attributes": {}, "type": "params", "children": [{"attributes": {"name": "renderer"}, "type": "param", "children": [{"attributes": {"text": "<p>the renderer</p>"}, "type": "desc"}, {"attributes": {}, "type": "types", "children": [{"attributes": {"type": "qx.ui.mobile.form.renderer.AbstractRenderer"}, "type": "entry"}]}]}]}, {"attributes": {"text": "<p>setter for the renderer private variable</p>"}, "type": "desc"}]}, {"attributes": {"docFrom": "qx.ui.form.Form", "line": 81, "overriddenFrom": "qx.ui.form.Form", "name": "validate"}, "type": "method"}]}]}